biomatools/__init__.py
biomatools/bioma_model.py
biomatools/calibration_task.py
biomatools/clients.py
biomatools/model_result.py
biomatools/model_run.py
biomatools/utils/__init__.py
biomatools/utils/abs.py
biomatools/utils/components.py
biomatools/utils/connection.py
biomatools/utils/formats.py
biomatools/utils/naming.py
bioma_modelling-0.0.1.dist-info/LICENSE
bioma_modelling-0.0.1.dist-info/METADATA
bioma_modelling-0.0.1.dist-info/WHEEL
bioma_modelling-0.0.1.dist-info/top_level.txt
bioma_modelling-0.0.1.dist-info/RECORD
