Metadata-Version: 2.1
Name: bioma-modelling
Version: 0.0.1
Summary: Python library to streamline interaction with the BioMA APIs, providing a pythonic facade to data and service access.
Home-page: https://dev.azure.com/dariodenart/_git/BioMA%20Python%20Toolkit
Author: CREA
Author-email: dario.denart@crea.gov.it
License: MIT
License-File: LICENSE
Requires-Dist: pandas
Requires-Dist: requests
Requires-Dist: retry
